<?xml version="1.0"?>
<!DOCTYPE hibernate-mapping PUBLIC "-//Hibernate/Hibernate Mapping DTD 3.0//EN"
"http://www.hibernate.org/dtd/hibernate-mapping-3.0.dtd">
<!-- Generated Nov 1, 2014 11:36:27 AM by Hibernate Tools 4.3.1 -->
<hibernate-mapping>
    <class name="myp.Tutorial" table="tutorial" catalog="hibernate">
        <id name="id" type="java.lang.Integer">
            <column name="id" />
            <generator class="identity"></generator>
        </id>
        <property name="sortdes" type="string">
            <column name="sortdes" length="45" not-null="true" />
        </property>
        <property name="longdes" type="string">
            <column name="longdes" length="45" not-null="true" />
        </property>
        <property name="pageurl" type="string">
            <column name="pageurl" length="45" not-null="true" />
        </property>
    </class>
</hibernate-mapping>
